Metadata-Version: 1.1
Name: omarbasiccalculator
Version: 0.0.1
Summary: Basic calculator Python package
Home-page: UNKNOWN
Author: Omar Fateh
Author-email: fatehomar0@gmail.com
License: UNKNOWN
Keywords: python,calculator package
Platform: UNKNOWN
Classifier: Development Status :: 3 - Alpha
Classifier: Intended Audience :: Education
Classifier: Programming Language :: Python :: 2
Classifier: Programming Language :: Python :: 3
Classifier: Operating System :: MacOS :: MacOS X
Classifier: Operating System :: Microsoft :: Windows
